_torch_migraphx.cpython-310-x86_64-linux-gnu.so
torch_migraphx-0.0.4.dist-info/LICENSE
torch_migraphx-0.0.4.dist-info/top_level.txt
torch_migraphx-0.0.4.dist-info/METADATA
torch_migraphx-0.0.4.dist-info/RECORD
torch_migraphx-0.0.4.dist-info/WHEEL
torch_migraphx/__init__.py
torch_migraphx/_C.py
torch_migraphx/csrc/mgx_util.cpp
torch_migraphx/csrc/torch_migraphx_py.cpp
torch_migraphx/csrc/mgx_util.h
torch_migraphx/csrc/par_for.h
torch_migraphx/fx/utils.py
torch_migraphx/fx/fx2mgx.py
torch_migraphx/fx/observer.py
torch_migraphx/fx/converter_registry.py
torch_migraphx/fx/mgx_module.py
torch_migraphx/fx/__init__.py
torch_migraphx/fx/lower_setting.py
torch_migraphx/fx/lower.py
torch_migraphx/fx/tools/mgx_splitter.py
torch_migraphx/fx/tools/timing_cache_utils.py
torch_migraphx/fx/tools/mgx_onnx.py
torch_migraphx/fx/tools/mgx_benchmark.py
torch_migraphx/fx/tools/__init__.py
torch_migraphx/fx/tools/mgx_minimizer.py
torch_migraphx/fx/passes/lower_basic_pass.py
torch_migraphx/fx/passes/remove_duplicate_output_args.py
torch_migraphx/fx/passes/lower_basic_pass_aten.py
torch_migraphx/fx/passes/__init__.py
torch_migraphx/fx/passes/lower_pass_manager_builder.py
torch_migraphx/fx/passes/graph_opts.py
torch_migraphx/fx/passes/pass_utils.py
torch_migraphx/fx/tracer/__init__.py
torch_migraphx/fx/tracer/acc_tracer/acc_op_properties.py
torch_migraphx/fx/tracer/acc_tracer/acc_shape_prop.py
torch_migraphx/fx/tracer/acc_tracer/acc_normalizer.py
torch_migraphx/fx/tracer/acc_tracer/acc_utils.py
torch_migraphx/fx/tracer/acc_tracer/__init__.py
torch_migraphx/fx/tracer/acc_tracer/acc_ops.py
torch_migraphx/fx/tracer/acc_tracer/acc_tracer.py
torch_migraphx/fx/tracer/aten_tracer/aten_tracer.py
torch_migraphx/fx/tracer/aten_tracer/__init__.py
torch_migraphx/fx/quantization/__init__.py
torch_migraphx/fx/quantization/mgx_qconfig.py
torch_migraphx/fx/quantization/mgx_backend_config.py
torch_migraphx/fx/converters/utils.py
torch_migraphx/fx/converters/aten_ops_converters.py
torch_migraphx/fx/converters/builtin_converters.py
torch_migraphx/fx/converters/acc_ops_converters.py
torch_migraphx/fx/converters/module_converters.py
