Metadata-Version: 2.1
Name: torch-migraphx
Version: 0.0.4
Summary: Intergrate PyTorch with MIGraphX acceleration engine
Home-page: https://github.com/ROCmSoftwarePlatform/torch_migraphx
Author: AMD
Author-email: Shivad.Bhavsar@amd.com
License: BSD
Platform: UNKNOWN
Classifier: Programming Language :: Python :: 3
Classifier: Programming Language :: C++
Classifier: License :: OSI Approved :: BSD License
Classifier: Operating System :: POSIX :: Linux
Classifier: Topic :: Scientific/Engineering :: Artificial Intelligence
Requires-Python: >=3.7
License-File: LICENSE
Requires-Dist: torch (>=1.11.0)
Requires-Dist: numpy (>=1.20.0)
Requires-Dist: pybind11-global
Requires-Dist: packaging
Requires-Dist: tabulate
